mc/__init__.py
mc/minecraft.py
mcapibridge-0.1.4.dist-info/licenses/LICENSE
mcapibridge-0.1.4.dist-info/METADATA
mcapibridge-0.1.4.dist-info/WHEEL
mcapibridge-0.1.4.dist-info/top_level.txt
mcapibridge-0.1.4.dist-info/RECORD
