Metadata-Version: 2.4
Name: mcapibridge
Version: 0.1.4
Summary: Python libary for MCAPIBridge
Author: TaotianZhufang
License: MIT License
Requires-Python: >=3.7
License-File: LICENSE
Dynamic: license-file
